[
  {
    "id": 55,
    "category_id": 6,
    "brand": "stone",
    "name": "Худи Stone island Off Dye",
    "description": "Очень классное худи. Плотное, самый хайп именно сейчас! Каждая вещь от Stone Island, линейки Off Dye, имеет свою уникальность, так как, все вещи Off Dye, окрашиваются в ручную, и одинаковых вещей этой линейки быть не может! Коллекция: 75. Размер по бирке: L. Фактический размер: L - XL.",
    "price_byn": 950.0,
    "prices": {
      "BYN": 950.0,
      "RUB": 27500.0,
      "USD": 355.0,
      "product_type": "stock",
      "condition": "Отличное",
      "extra_photos_url": "https://t.me/mestniybaryga/9658"
    },
    "sizes": [
      "L-XL"
    ],
    "stock": 1,
    "product_type": "stock",
    "section": "stock",
    "condition": "Отличное",
    "extra_photos_url": "https://t.me/mestniybaryga/9658",
    "images": [
      "https://liknine.github.io/mestniybot/images/product_55_c66d4a70.jpg",
      "https://liknine.github.io/mestniybot/images/product_55_8655fd33.jpg",
      "https://liknine.github.io/mestniybot/images/product_55_4bd41869.jpg",
      "https://liknine.github.io/mestniybot/images/product_55_7dbdd4cf.jpg",
      "https://liknine.github.io/mestniybot/images/product_55_c548d80d.jpg"
    ]
  },
  {
    "id": 76,
    "category_id": 5,
    "brand": "polo",
    "name": "Поло Ralph Lauren",
    "description": "Темное, классное поло от Polo Ralph Lauren. Необычный дизайн за счет множества логотипов. Размер: XL.",
    "price_byn": 85.0,
    "prices": {
      "BYN": 85.0,
      "RUB": 2900.0,
      "USD": 31.0,
      "product_type": "stock",
      "condition": "Отличное",
      "extra_photos_url": "https://t.me/mestniybaryga/9894"
    },
    "sizes": [
      "XL"
    ],
    "stock": 1,
    "product_type": "stock",
    "section": "stock",
    "condition": "Отличное",
    "extra_photos_url": "https://t.me/mestniybaryga/9894",
    "images": [
      "https://liknine.github.io/mestniybot/images/product_76_49877aa1.jpg",
      "https://liknine.github.io/mestniybot/images/product_76_d455aeee.jpg",
      "https://liknine.github.io/mestniybot/images/product_76_3f7d7ede.jpg",
      "https://liknine.github.io/mestniybot/images/product_76_aea4847e.jpg",
      "https://liknine.github.io/mestniybot/images/product_76_1c2ccd86.jpg"
    ]
  },
  {
    "id": 78,
    "category_id": 6,
    "brand": "weekend",
    "name": "Лонгслив Weekend Offender НОВЫЙ",
    "description": "Абсолютно новый, с навесной биркой ( этикеткой ). Оригинал. Размер: L. Оригинал, классный принт спереди.",
    "price_byn": 150.0,
    "prices": {
      "BYN": 150.0,
      "RUB": 4700.0,
      "USD": 56.0,
      "product_type": "stock",
      "condition": "Новое",
      "extra_photos_url": "https://t.me/mestniybaryga/9951"
    },
    "sizes": [
      "L"
    ],
    "stock": 1,
    "product_type": "stock",
    "section": "stock",
    "condition": "Новое",
    "extra_photos_url": "https://t.me/mestniybaryga/9951",
    "images": [
      "https://liknine.github.io/mestniybot/images/product_78_107febe6.jpg",
      "https://liknine.github.io/mestniybot/images/product_78_3695f1dd.jpg",
      "https://liknine.github.io/mestniybot/images/product_78_199b7c6e.jpg",
      "https://liknine.github.io/mestniybot/images/product_78_44c62759.jpg",
      "https://liknine.github.io/mestniybot/images/product_78_89143d98.jpg"
    ]
  },
  {
    "id": 79,
    "category_id": 6,
    "brand": "stone",
    "name": "Зип - Худи Stone Island",
    "description": "Классный цвет. Плотный материал, удобная. База, с патчем на рукаве, все, как мы любим. Коллекция: 61. Оригинал.",
    "price_byn": 450.0,
    "prices": {
      "BYN": 450.0,
      "RUB": 13100.0,
      "USD": 168.0,
      "product_type": "stock",
      "condition": "Отличное",
      "extra_photos_url": "https://t.me/mestniybaryga/9956"
    },
    "sizes": [
      "L"
    ],
    "stock": 1,
    "product_type": "stock",
    "section": "stock",
    "condition": "Отличное",
    "extra_photos_url": "https://t.me/mestniybaryga/9956",
    "images": [
      "https://liknine.github.io/mestniybot/images/product_79_bd95a6bd.jpg",
      "https://liknine.github.io/mestniybot/images/product_79_2df86c67.jpg",
      "https://liknine.github.io/mestniybot/images/product_79_aa9137ed.jpg",
      "https://liknine.github.io/mestniybot/images/product_79_c5bd0e72.jpg",
      "https://liknine.github.io/mestniybot/images/product_79_fd94aac3.jpg"
    ]
  },
  {
    "id": 86,
    "category_id": 1,
    "brand": "nike",
    "name": "Nike Air Max 1 НОВЫЕ",
    "description": "Абсолютно новая, классная, яркая пара. В комплекте идут с коробкой, отлично сидят на ноге. Самое то, на текущий сезон. Размеры:\n42 ( 26.5 СМ стелька )\n44 ( 28 СМ стелька )",
    "price_byn": 350.0,
    "prices": {
      "BYN": 350.0,
      "RUB": 10300.0,
      "USD": 131.0,
      "product_type": "stock",
      "condition": "Новое",
      "extra_photos_url": "https://t.me/mestniybaryga/10022"
    },
    "sizes": [
      "42",
      "44"
    ],
    "stock": 1,
    "product_type": "stock",
    "section": "stock",
    "condition": "Новое",
    "extra_photos_url": "https://t.me/mestniybaryga/10022",
    "images": [
      "https://liknine.github.io/mestniybot/images/product_86_2e4d5e9c.jpg",
      "https://liknine.github.io/mestniybot/images/product_86_f4edf97e.jpg",
      "https://liknine.github.io/mestniybot/images/product_86_b624af4f.jpg",
      "https://liknine.github.io/mestniybot/images/product_86_eb5c7313.jpg",
      "https://liknine.github.io/mestniybot/images/product_86_b9fca136.jpg"
    ]
  },
  {
    "id": 88,
    "category_id": 1,
    "brand": "adidas",
    "name": "Кроссовки Adidas Crazychaos 2000 НОВЫЕ",
    "description": "Абсолютно новые, классная, и очень удобная пара. В комплекте с коробкой, и этикеткой. Размер по бирке: \n43 1/3 | 27.5 СМ\n44 | 28 СМ",
    "price_byn": 270.0,
    "prices": {
      "BYN": 270.0,
      "RUB": 8000.0,
      "USD": 101.0,
      "product_type": "stock",
      "condition": "Новое",
      "extra_photos_url": "https://t.me/mestniybaryga/10037"
    },
    "sizes": [
      "43",
      "44"
    ],
    "stock": 2,
    "product_type": "stock",
    "section": "stock",
    "condition": "Новое",
    "extra_photos_url": "https://t.me/mestniybaryga/10037",
    "images": [
      "https://liknine.github.io/mestniybot/images/product_88_04f643c0.jpg",
      "https://liknine.github.io/mestniybot/images/product_88_8ddd83af.jpg",
      "https://liknine.github.io/mestniybot/images/product_88_05f6da64.jpg",
      "https://liknine.github.io/mestniybot/images/product_88_c45c3e0f.jpg",
      "https://liknine.github.io/mestniybot/images/product_88_2e3a687d.jpg"
    ]
  },
  {
    "id": 89,
    "category_id": 1,
    "brand": "raf",
    "name": "Кроссовки Raf Simons Ultrasceptre",
    "description": "Очень хорошее состояние! Очень близки к полному идеалу! Размер по бирке 40, но данная модель всегда большемерит. Фактический размер: 41.5 ( 26.5 СМ по стельке )",
    "price_byn": 600.0,
    "prices": {
      "BYN": 600.0,
      "RUB": 17300.0,
      "USD": 224.0,
      "product_type": "stock",
      "condition": "Отличное",
      "extra_photos_url": "https://t.me/mestniybaryga/10043"
    },
    "sizes": [
      "41.5"
    ],
    "stock": 1,
    "product_type": "stock",
    "section": "stock",
    "condition": "Отличное",
    "extra_photos_url": "https://t.me/mestniybaryga/10043",
    "images": [
      "https://liknine.github.io/mestniybot/images/product_89_db06717c.jpg",
      "https://liknine.github.io/mestniybot/images/product_89_94605bc7.jpg",
      "https://liknine.github.io/mestniybot/images/product_89_3ed0940f.jpg",
      "https://liknine.github.io/mestniybot/images/product_89_2e6afcd5.jpg",
      "https://liknine.github.io/mestniybot/images/product_89_9842d092.jpg"
    ]
  },
  {
    "id": 90,
    "category_id": 1,
    "brand": "nike",
    "name": "Кроссовки Nike Air Max 1 НОВЫЕ",
    "description": "Очень классные, удобные, абсолютно новые, оригинал. В комплекте с коробкой. Размер по бирке: 42.5 | 27 СМ ( по стельке )",
    "price_byn": 350.0,
    "prices": {
      "BYN": 350.0,
      "RUB": 10300.0,
      "USD": 131.0,
      "product_type": "stock",
      "condition": "Новое",
      "extra_photos_url": "https://t.me/mestniybaryga/10048"
    },
    "sizes": [
      "42.5"
    ],
    "stock": 1,
    "product_type": "stock",
    "section": "stock",
    "condition": "Новое",
    "extra_photos_url": "https://t.me/mestniybaryga/10048",
    "images": [
      "https://liknine.github.io/mestniybot/images/product_90_06591371.jpg",
      "https://liknine.github.io/mestniybot/images/product_90_680d4f79.jpg",
      "https://liknine.github.io/mestniybot/images/product_90_76ddd97f.jpg",
      "https://liknine.github.io/mestniybot/images/product_90_7d86ab45.jpg",
      "https://liknine.github.io/mestniybot/images/product_90_ab0d9fe8.jpg"
    ]
  },
  {
    "id": 91,
    "category_id": 6,
    "brand": "stone",
    "name": "Свитшот Stone Island Junior",
    "description": "Классный, плотный. Состояние отличное, есть следы носок. Коллекция: 73. Размер по бирке: 14/170. Фактический размер: S - M.",
    "price_byn": 230.0,
    "prices": {
      "BYN": 230.0,
      "RUB": 6900.0,
      "USD": 86.0,
      "product_type": "stock",
      "condition": "Отличное",
      "extra_photos_url": "https://t.me/mestniystore/10141"
    },
    "sizes": [
      "S-M"
    ],
    "stock": 1,
    "product_type": "stock",
    "section": "stock",
    "condition": "Отличное",
    "extra_photos_url": "https://t.me/mestniystore/10141",
    "images": [
      "https://liknine.github.io/mestniybot/images/product_91_3a9454ee.jpg",
      "https://liknine.github.io/mestniybot/images/product_91_4ede2fc7.jpg",
      "https://liknine.github.io/mestniybot/images/product_91_1ee03ce5.jpg",
      "https://liknine.github.io/mestniybot/images/product_91_9a4a3cb8.jpg",
      "https://liknine.github.io/mestniybot/images/product_91_77cfbfba.jpg"
    ]
  }
]